jenkins_pysdk/__init__.py
jenkins_pysdk/_logger.py
jenkins_pysdk/builders.py
jenkins_pysdk/builds.py
jenkins_pysdk/consts.py
jenkins_pysdk/core.py
jenkins_pysdk/credentials.py
jenkins_pysdk/exceptions.py
jenkins_pysdk/jenkins.py
jenkins_pysdk/jobs.py
jenkins_pysdk/nodes.py
jenkins_pysdk/objects.py
jenkins_pysdk/plugins.py
jenkins_pysdk/queues.py
jenkins_pysdk/users.py
jenkins_pysdk/utils.py
jenkins_pysdk/version.py
jenkins_pysdk/views.py
jenkins_pysdk/workspace.py
tests/__init__.py
tests/conf.py
tests/jenkins_test.py
jenkins_pysdk-1.4.4.dist-info/LICENSE
jenkins_pysdk-1.4.4.dist-info/METADATA
jenkins_pysdk-1.4.4.dist-info/WHEEL
jenkins_pysdk-1.4.4.dist-info/top_level.txt
jenkins_pysdk-1.4.4.dist-info/RECORD
