Metadata-Version: 2.1
Name: jenkins_pysdk
Version: 1.4.4
Summary: 2024 Python SDK for Jenkins
Home-page: https://github.com/KnownZero/JenkinsPythonSDK
Author: KnownZero
Author-email: gihjeefs@protonmail.com
License: MIT
Keywords: python,Jenkins,SDK,API,REST
Classifier: Development Status :: 5 - Production/Stable
Classifier: License :: OSI Approved :: MIT License
Classifier: Operating System :: OS Independent
Classifier: Intended Audience :: Developers
Classifier: Programming Language :: Python :: 3.7
Classifier: Programming Language :: Python :: 3.8
Classifier: Programming Language :: Python :: 3.9
Classifier: Programming Language :: Python :: 3.10
Classifier: Programming Language :: Python :: 3.11
Classifier: Programming Language :: Python :: 3.12
Requires-Python: >=3.7
License-File: LICENSE
Requires-Dist: httpx
Requires-Dist: urllib3
